datasette_os_info/__init__.py
datasette_os_info-0.1.dist-info/licenses/LICENSE
datasette_os_info-0.1.dist-info/METADATA
datasette_os_info-0.1.dist-info/WHEEL
datasette_os_info-0.1.dist-info/entry_points.txt
datasette_os_info-0.1.dist-info/top_level.txt
datasette_os_info-0.1.dist-info/RECORD
