Metadata-Version: 2.4
Name: datasette-os-info
Version: 0.1
Summary: Provide information about the current OS at /-/os
Author: Simon Willison
License-Expression: Apache-2.0
Project-URL: Homepage, https://github.com/datasette/datasette-os-info
Project-URL: Changelog, https://github.com/datasette/datasette-os-info/releases
Project-URL: Issues, https://github.com/datasette/datasette-os-info/issues
Project-URL: CI, https://github.com/datasette/datasette-os-info/actions
Classifier: Framework :: Datasette
Requires-Python: >=3.10
License-File: LICENSE
Requires-Dist: datasette
Provides-Extra: test
Requires-Dist: pytest; extra == "test"
Requires-Dist: pytest-asyncio; extra == "test"
Dynamic: license-file
